iobind/__init__.py
iobind-0.0.1.dist-info/METADATA
iobind-0.0.1.dist-info/WHEEL
iobind-0.0.1.dist-info/top_level.txt
iobind-0.0.1.dist-info/RECORD
