Metadata-Version: 2.1
Name: iobind
Version: 0.0.1
Summary: Define inputs and outputs
Home-page: http://github.com/hal9ai/iobind
Author: Javier Luraschi
Author-email: javier@hal9.ai
License: MIT
Platform: UNKNOWN
